LICENSE
MANIFEST.in
README.rst
setup.cfg
setup.py
Flask_SuperAdmin.egg-info/PKG-INFO
Flask_SuperAdmin.egg-info/SOURCES.txt
Flask_SuperAdmin.egg-info/dependency_links.txt
Flask_SuperAdmin.egg-info/not-zip-safe
Flask_SuperAdmin.egg-info/requires.txt
Flask_SuperAdmin.egg-info/top_level.txt
flask_superadmin/__init__.py
flask_superadmin/babel.py
flask_superadmin/base.py
flask_superadmin/form.py
flask_superadmin/tools.py
flask_superadmin/contrib/__init__.py
flask_superadmin/contrib/djangomodel.py
flask_superadmin/contrib/fileadmin.py
flask_superadmin/contrib/mongoenginemodel.py
flask_superadmin/contrib/sqlamodel.py
flask_superadmin/model/__init__.py
flask_superadmin/model/base.py
flask_superadmin/model/filters.py
flask_superadmin/model/backends/__init__.py
flask_superadmin/model/backends/django/__init__.py
flask_superadmin/model/backends/django/fields.py
flask_superadmin/model/backends/django/orm.py
flask_superadmin/model/backends/django/view.py
flask_superadmin/model/backends/mongoengine/__init__.py
flask_superadmin/model/backends/mongoengine/fields.py
flask_superadmin/model/backends/mongoengine/orm.py
flask_superadmin/model/backends/mongoengine/view.py
flask_superadmin/model/backends/sqlalchemy/__init__.py
flask_superadmin/model/backends/sqlalchemy/filters.py
flask_superadmin/model/backends/sqlalchemy/orm.py
flask_superadmin/model/backends/sqlalchemy/tools.py
flask_superadmin/model/backends/sqlalchemy/view.py
flask_superadmin/static/bootstrap/css/bootstrap-responsive.css
flask_superadmin/static/bootstrap/css/bootstrap-responsive.min.css
flask_superadmin/static/bootstrap/css/bootstrap.css
flask_superadmin/static/bootstrap/css/bootstrap.min.css
flask_superadmin/static/bootstrap/img/glyphicons-halflings-white.png
flask_superadmin/static/bootstrap/img/glyphicons-halflings.png
flask_superadmin/static/bootstrap/js/admin.js
flask_superadmin/static/bootstrap/js/bootstrap.js
flask_superadmin/static/bootstrap/js/bootstrap.min.js
flask_superadmin/static/chosen/chosen-sprite.png
flask_superadmin/static/chosen/chosen.css
flask_superadmin/static/chosen/chosen.jquery.min.js
flask_superadmin/static/css/admin.css
flask_superadmin/static/css/datepicker.css
flask_superadmin/static/css/file.css
