Metadata-Version: 1.0
Name: Flask-SuperAdmin
Version: 1.7
Summary: The best admin interface framework for Python. With scaffolding for MongoEngine, Django and SQLAlchemy.
Home-page: https://github.com/syrusakbary/flask-superadmin/
Author: Syrus Akbary
Author-email: me@syrusakbary.com
License: BSD
Platform: any
Classifier: Development Status :: 3 - Alpha
Classifier: Environment :: Web Environment
Classifier: Intended Audience :: Developers
Classifier: License :: OSI Approved :: BSD License
Classifier: Operating System :: OS Independent
Classifier: Programming Language :: Python
Classifier: Topic :: Software Development :: Libraries :: Python Modules
